gen3_util_plugin_nvidia/__init__.py
plugins/__init__.py
plugins/gen3_util_plugin_nvidia/__init__.py
gen3_util_plugin_nvidia-0.0.4.dist-info/METADATA
gen3_util_plugin_nvidia-0.0.4.dist-info/WHEEL
gen3_util_plugin_nvidia-0.0.4.dist-info/entry_points.txt
gen3_util_plugin_nvidia-0.0.4.dist-info/top_level.txt
gen3_util_plugin_nvidia-0.0.4.dist-info/RECORD
