Metadata-Version: 2.1
Name: gen3-util-plugin-nvidia
Version: 0.0.4
Summary: CEDAR / NVIDIA collaboration
Home-page: https://github.com/ACED-IDP/nvidia-collaboration
Author: compbio
License: UNKNOWN
Project-URL: Bug Reports, https://github.com/ACED-IDP/nvidia_collaboration/issues
Project-URL: Source, https://github.com/ACED-IDP/nvidia_collaboration
Keywords: bioinformatics
Platform: UNKNOWN
Classifier: Development Status :: 3 - Alpha
Classifier: Intended Audience :: Developers
Classifier: Topic :: Software Development :: Build Tools
Classifier: License :: OSI Approved :: MIT License
Classifier: Programming Language :: Python :: 3.9
Requires-Python: >=3.9, <4
Requires-Dist: gen3-util
